instrumental_agent/__init__.py
instrumental_agent/agent.py
instrumental_agent-1.3.0.dist-info/DESCRIPTION.rst
instrumental_agent-1.3.0.dist-info/METADATA
instrumental_agent-1.3.0.dist-info/RECORD
instrumental_agent-1.3.0.dist-info/WHEEL
instrumental_agent-1.3.0.dist-info/metadata.json
instrumental_agent-1.3.0.dist-info/top_level.txt
