Metadata-Version: 2.0
Name: instrumental-agent
Version: 1.3.0
Summary: A wrapper for the Instrumental service.
Home-page: https://github.com/instrumental/instrumental_agent-python
Author: Instrumental Support
Author-email: support@instrumentalapp.com
License: UNKNOWN
Keywords: Instrumental,API,Metrics,APM
Platform: UNKNOWN
Classifier: Development Status :: 5 - Production/Stable
Classifier: Environment :: Web Environment
Classifier: Intended Audience :: Developers
Classifier: Intended Audience :: Information Technology
Classifier: Operating System :: Microsoft :: Windows
Classifier: Operating System :: POSIX
Classifier: Operating System :: Unix
